demo/manage.py
demo/setup.py
demo/demo/__init__.py
demo/demo/gunicorn_config.py
demo/demo/settings.py
demo/demo/settings_docker.py
demo/demo/urls.py
demo/demo/wsgi.py
demo/demo/core/__init__.py
demo/demo/core/admin.py
demo/demo/core/apps.py
demo/demo/core/forms.py
demo/demo/core/jobs.py
demo/demo/core/models.py
demo/demo/core/tests.py
demo/demo/core/urls.py
demo/demo/core/views.py
demo/demo/core/wildewidgets.py
demo/demo/core/migrations/0001_initial.py
demo/demo/core/migrations/0002_initial_data.py
demo/demo/core/migrations/__init__.py
demo/demo/core/templatetags/__init__.py
demo/demo/users/__init__.py
demo/demo/users/apps.py
demo/demo/users/models.py
demo/demo/users/tests.py
demo/demo/users/migrations/0001_initial.py
demo/demo/users/migrations/0002_load_fixture.py
demo/demo/users/migrations/__init__.py
demo/etc/ipython_config.py
django_wildewidgets-1.2.5.dist-info/licenses/LICENSE.txt
docs/conf.py
wildewidgets/__init__.py
wildewidgets/admin.py
wildewidgets/apps.py
wildewidgets/forms.py
wildewidgets/menus.py
wildewidgets/models.py
wildewidgets/settings.py
wildewidgets/tests.py
wildewidgets/viewsets.py
wildewidgets/static/wildewidgets/css/_navbar.scss
wildewidgets/static/wildewidgets/css/_toggleablemanytomanyfieldblock.scss
wildewidgets/static/wildewidgets/css/_widget-index.scss
wildewidgets/static/wildewidgets/css/_widget-list.scss
wildewidgets/static/wildewidgets/css/highlighting.css
wildewidgets/static/wildewidgets/css/table_extra.css
wildewidgets/static/wildewidgets/css/wildewidgets.css
wildewidgets/static/wildewidgets/css/wildewidgets.scss
wildewidgets/static/wildewidgets/images/placeholder.png
wildewidgets/static/wildewidgets/js/wildewidgets.js
wildewidgets/templates/.DS_Store
wildewidgets/templates/wildewidgets/altairchart.html
wildewidgets/templates/wildewidgets/apex_chart.html
wildewidgets/templates/wildewidgets/apex_json.html
wildewidgets/templates/wildewidgets/barchart.html
wildewidgets/templates/wildewidgets/block--simple.html
wildewidgets/templates/wildewidgets/block.html
django_wildewidgets-1.2.5.dist-info/METADATA
django_wildewidgets-1.2.5.dist-info/WHEEL
django_wildewidgets-1.2.5.dist-info/top_level.txt
django_wildewidgets-1.2.5.dist-info/RECORD
