Metadata-Version: 2.4
Name: django_wildewidgets
Version: 1.2.5
Summary: django-wildewidgets is a Django design library providing several tools for building full-featured, widget-based web applications with a standard, consistent design, based on Bootstrap.
Author-email: Caltech IMSS ADS <imss-ads-staff@caltech.edu>
Project-URL: Homepage, https://github.com/caltechads/django-wildewidgets
Keywords: design,widget,django
Classifier: Development Status :: 5 - Production/Stable
Classifier: Intended Audience :: Developers
Classifier: Operating System :: OS Independent
Classifier: Programming Language :: Python
Classifier: Programming Language :: Python :: 3.10
Classifier: Programming Language :: Python :: 3.11
Classifier: Programming Language :: Python :: 3.12
Classifier: Programming Language :: Python :: 3.13
Classifier: Framework :: Django
Classifier: Framework :: Django :: 4.2
Classifier: Framework :: Django :: 5
Classifier: Framework :: Django :: 5.1
Classifier: Framework :: Django :: 5.2
Requires-Python: >=3.10
License-File: LICENSE.txt
Requires-Dist: django>=5.1
Requires-Dist: django-crispy-forms>=2.4
Requires-Dist: crispy-bootstrap5>=2025.6
Dynamic: license-file
